[
  {
    "name": "components-contact",
    "path": "/components/contact",
    "component": "C:\\\\newportfolio\\\\web\\\\pages\\\\components\\\\contact.vue",
    "chunkName": "pages/components/contact",
    "_name": "_adbf6346"
  },
  {
    "name": "components-main-section",
    "path": "/components/main-section",
    "component": "C:\\\\newportfolio\\\\web\\\\pages\\\\components\\\\main-section.vue",
    "chunkName": "pages/components/main-section",
    "_name": "_d4cc0f38"
  },
  {
    "name": "components-project",
    "path": "/components/project",
    "component": "C:\\\\newportfolio\\\\web\\\\pages\\\\components\\\\project.vue",
    "chunkName": "pages/components/project",
    "_name": "_6eab50d6"
  },
  {
    "name": "components-project-detail",
    "path": "/components/project-detail",
    "component": "C:\\\\newportfolio\\\\web\\\\pages\\\\components\\\\project-detail.vue",
    "chunkName": "pages/components/project-detail",
    "_name": "_58f7b350"
  },
  {
    "name": "components-sub-section1",
    "path": "/components/sub-section1",
    "component": "C:\\\\newportfolio\\\\web\\\\pages\\\\components\\\\sub-section1.vue",
    "chunkName": "pages/components/sub-section1",
    "_name": "_60f37f28"
  },
  {
    "name": "components-sub-section2",
    "path": "/components/sub-section2",
    "component": "C:\\\\newportfolio\\\\web\\\\pages\\\\components\\\\sub-section2.vue",
    "chunkName": "pages/components/sub-section2",
    "_name": "_60d75026"
  },
  {
    "name": "components-sub-section3",
    "path": "/components/sub-section3",
    "component": "C:\\\\newportfolio\\\\web\\\\pages\\\\components\\\\sub-section3.vue",
    "chunkName": "pages/components/sub-section3",
    "_name": "_60bb2124"
  },
  {
    "name": "index",
    "path": "/",
    "component": "C:\\\\newportfolio\\\\web\\\\pages\\\\index.vue",
    "chunkName": "pages/index",
    "_name": "_09194fb6"
  }
]
